odoo/addons/maintenance_location_hr/README.rst
odoo/addons/maintenance_location_hr/__init__.py
odoo/addons/maintenance_location_hr/__manifest__.py
odoo/addons/maintenance_location_hr/i18n/es.po
odoo/addons/maintenance_location_hr/i18n/fr.po
odoo/addons/maintenance_location_hr/i18n/it.po
odoo/addons/maintenance_location_hr/i18n/maintenance_location_hr.pot
odoo/addons/maintenance_location_hr/models/__init__.py
odoo/addons/maintenance_location_hr/models/maintenance_equipment.py
odoo/addons/maintenance_location_hr/models/maintenance_location.py
odoo/addons/maintenance_location_hr/readme/CONTRIBUTORS.rst
odoo/addons/maintenance_location_hr/readme/DESCRIPTION.rst
odoo/addons/maintenance_location_hr/static/description/icon.png
odoo/addons/maintenance_location_hr/static/description/index.html
odoo/addons/maintenance_location_hr/tests/__init__.py
odoo/addons/maintenance_location_hr/tests/test_maintenance_location_hr.py
odoo/addons/maintenance_location_hr/views/maintenance_equipment.xml
odoo/addons/maintenance_location_hr/views/maintenance_location.xml
odoo14_addon_maintenance_location_hr-14.0.1.0.1.dev8.dist-info/METADATA
odoo14_addon_maintenance_location_hr-14.0.1.0.1.dev8.dist-info/WHEEL
odoo14_addon_maintenance_location_hr-14.0.1.0.1.dev8.dist-info/top_level.txt
odoo14_addon_maintenance_location_hr-14.0.1.0.1.dev8.dist-info/RECORD
